{
	"arm-cp-islands.NumCBZ": 39,
	"arm-cp-islands.NumT2BrShrunk": 704,
	"arm-cp-islands.NumTBs": 6,
	"arm-isel.NumMovwMovt": 47,
	"asm-printer.EmittedInsts": 4815,
	"assembler.EmittedAlignFragments": 241,
	"assembler.EmittedDataFragments": 2441,
	"assembler.EmittedFragments": 5283,
	"assembler.EmittedRelaxableFragments": 704,
	"assembler.FragmentLayouts": 5299,
	"assembler.ObjectBytes": 277656,
	"assembler.RelaxationSteps": 2,
	"assembler.evaluateFixup": 11625,
	"build-libcalls.NumNoCapture": 1,
	"build-libcalls.NumNoUnwind": 1,
	"build-libcalls.NumReadOnlyArg": 1,
	"cgscc-passmgr.MaxSCCIterations": 1,
	"constmerge.NumIdenticalMerged": 2,
	"dagcombine.NodesCombined": 1011,
	"dagcombine.PostIndexedNodes": 1,
	"deadargelim.NumArgumentsEliminated": 15,
	"deadargelim.NumRetValsEliminated": 7,
	"globaldce.NumFunctions": 2,
	"globaldce.NumVariables": 4,
	"globalopt.NumDeleted": 2,
	"globalopt.NumMarked": 4,
	"globalopt.NumUnnamed": 92,
	"globalsmodref-aa.NumNoMemFunctions": 2,
	"globalsmodref-aa.NumNonAddrTakenFunctions": 53,
	"globalsmodref-aa.NumNonAddrTakenGlobalVars": 10,
	"globalsmodref-aa.NumReadMemFunctions": 3,
	"isel.NumDAGBlocks": 593,
	"isel.NumDAGIselRetries": 72810,
	"isel.NumEntryBlocks": 75,
	"livedebugvars.NumInsertedDebugLabels": 1,
	"localstackalloc.NumAllocations": 168,
	"mccodeemitter.MCNumEmitted": 4809,
	"mcexpr.MCExprEvaluate": 61012,
	"phi-node-elimination.NumLowered": 8,
	"pre-RA-sched.LoadsClustered": 82,
	"prologepilog.NumBytesStackSpace": 1276,
	"prologepilog.NumFuncSeen": 75,
	"prologepilog.NumLeafFuncWithSpills": 2,
	"regalloc.NumAssigned": 2845,
	"regalloc.NumDCEDeleted": 23,
	"regalloc.NumEvicted": 59,
	"regalloc.NumIdCopies": 243,
	"regalloc.NumNewQueued": 59,
	"regalloc.NumReMats": 25,
	"regalloc.NumShrinkToUses": 25,
	"regalloc.NumUnassigned": 59,
	"regalloc.numCrossRCs": 20,
	"regalloc.numJoins": 48,
	"sccp.IPNumArgsElimed": 15,
	"sccp.IPNumGlobalConst": 1,
	"sccp.IPNumInstRemoved": 10,
	"sccp.NumDeadBlocks": 2,
	"sccp.NumInstRemoved": 2,
	"stackmaps.NumStackMapFuncSkipped": 75,
	"stackmaps.NumStackMapFuncVisited": 75,
	"t2-reduce-size.Num2Addrs": 458,
	"t2-reduce-size.NumLdSts": 1912,
	"t2-reduce-size.NumNarrows": 419,
	"thumb2-it.NumITs": 1,
	"twoaddressinstruction.NumTwoAddressInstrs": 5
}
